<?xml version="1.0" encoding="UTF-8"?>
<pairLibraryItem>
    <structureName>MosfetDiodeStack</structureName>
    <structureSymmetry>false</structureSymmetry>
    <pairConnection>
        <pairPinType>
            <structurePinType>
                <structureName>MosfetDiodeStack</structureName>
                <structurePinName>Drain</structurePinName>
            </structurePinType>
            <childPinType>
                <childNumber>1</childNumber>
                <structurePinType>
                    <structureName>MosfetDiodeArray</structureName>
                    <structurePinName>Drain</structurePinName>
                </structurePinType>
            </childPinType>
        </pairPinType>
        <pairPinType>
            <structurePinType>
                <structureName>MosfetDiodeStack</structureName>
                <structurePinName>Inner</structurePinName>
            </structurePinType>
            <childPinType>
                <childNumber>1</childNumber>
                <structurePinType>
                    <structureName>MosfetDiodeArray</structureName>
                    <structurePinName>Source</structurePinName>
                </structurePinType>
            </childPinType>
        </pairPinType>
        <pairPinType>
            <structurePinType>
                <structureName>MosfetDiodeStack</structureName>
                <structurePinName>Source</structurePinName>
            </structurePinType>
            <childPinType>
                <childNumber>2</childNumber>
                <structurePinType>
                    <structureName>MosfetDiodeArray</structureName>
                    <structurePinName>Source</structurePinName>
                </structurePinType>
            </childPinType>
        </pairPinType>
    </pairConnection>
    <characteristicConnection>
        <firstChildPinType>
            <structureName>MosfetDiodeArray</structureName>
            <structurePinName>Source</structurePinName>
        </firstChildPinType>
        <secondChildPinType>
            <structureName>MosfetDiodeArray</structureName>
            <structurePinName>Drain</structurePinName>
        </secondChildPinType>
    </characteristicConnection>
    <recognitionRules>
        <techTypeRule attribute="same"/>
        <netRules>
        </netRules>
        <connectionRules>     
            <connectionRule>
                <connected>false</connected>
                <firstChildPinType>
                    <structureName>MosfetDiodeArray</structureName>
                    <structurePinName>Drain</structurePinName>
                </firstChildPinType>
                <secondChildPinType>
                    <structureName>MosfetDiodeArray</structureName>
                    <structurePinName>Source</structurePinName>
                </secondChildPinType>
            </connectionRule>
        </connectionRules>
    </recognitionRules>
</pairLibraryItem>
